README.txt
setup.cfg
setup.py
docs/HISTORY.txt
docs/LICENSE.GPL
docs/LICENSE.txt
docs/MANUAL.txt
raptus/__init__.py
raptus.article.randomimage.egg-info/PKG-INFO
raptus.article.randomimage.egg-info/SOURCES.txt
raptus.article.randomimage.egg-info/dependency_links.txt
raptus.article.randomimage.egg-info/entry_points.txt
raptus.article.randomimage.egg-info/namespace_packages.txt
raptus.article.randomimage.egg-info/not-zip-safe
raptus.article.randomimage.egg-info/requires.txt
raptus.article.randomimage.egg-info/top_level.txt
raptus/article/__init__.py
raptus/article/randomimage/__init__.py
raptus/article/randomimage/configure.zcml
raptus/article/randomimage/interfaces.py
raptus/article/randomimage/randomimage.py
raptus/article/randomimage/browser/__init__.py
raptus/article/randomimage/browser/configure.zcml
raptus/article/randomimage/browser/randomimage.pt
raptus/article/randomimage/browser/randomimage.py
raptus/article/randomimage/browser/randomimage_full.gif
raptus/article/randomimage/browser/randomimage_left.gif
raptus/article/randomimage/browser/randomimage_right.gif
raptus/article/randomimage/browser/randomimage_teaser.gif
raptus/article/randomimage/i18n/raptus.article-de.po
raptus/article/randomimage/i18n/raptus.article-fr.po
raptus/article/randomimage/i18n/raptus.article.pot
raptus/article/randomimage/profiles/default/metadata.xml
raptus/article/randomimage/profiles/default/propertiestool.xml
raptus/article/randomimage/profiles/default/viewlets.xml