Metadata-Version: 1.0
Name: raptus.article.randomimage
Version: 2.0b5
Summary: Provides components which display a random image contained in the article.
Home-page: http://raptus.com
Author: Raptus AG
Author-email: dev@raptus.com
License: GPL
Platform: UNKNOWN
Classifier: Programming Language :: Python
Classifier: Topic :: Software Development :: Libraries :: Python Modules
